sct/__init__.py
sct/composition.py
sct/demo.py
sct/routes.py
sct/boilerplate/__init__.py
sct/boilerplate/html.py
sct/boilerplate/sst.py
sct/component/__init__.py
sct/component/hierarchy.py
sct/component/node.py
sct/component/tree.py
sct/db/__init__.py
sct/db/checkpoint.py
sct/db/sstinfo.py
sct/sst_ct.egg-info/PKG-INFO
sct/sst_ct.egg-info/SOURCES.txt
sct/sst_ct.egg-info/dependency_links.txt
sct/sst_ct.egg-info/requires.txt
sct/sst_ct.egg-info/top_level.txt
sct/static/css/beautiful.css
sct/static/css/drawflow.min.css
sct/static/css/index.css
sct/static/css/micromodal.css
sct/static/img/add-icon.png
sct/static/img/remove-icon.png
sct/static/js/html.js
sct/static/js/modal.js
sct/static/js/drawflow/drawflow.min.js
sct/static/js/drawflow/event.js
sct/static/js/drawflow/module.js
sct/templates/base.html
sct/templates/canvas.html
sct/templates/index.html
sct/templates/modal.html
sct/templates/run.py
sct/templates/scripts.html
sct/templates/styles.html
sst_ct-0.0.10.dist-info/METADATA
sst_ct-0.0.10.dist-info/WHEEL
sst_ct-0.0.10.dist-info/top_level.txt
sst_ct-0.0.10.dist-info/RECORD
