Metadata-Version: 2.1
Name: sst-ct
Version: 0.0.10
Summary: SST Hierarchical Composition Tool
Author-email: lpsmodsim <modsim@lps.umd.edu>
Project-URL: Homepage, https://github.com/lpsmodsimteam/sst-composition-tool
Classifier: Programming Language :: Python :: 3
Classifier: License :: OSI Approved :: MIT License
Classifier: Operating System :: OS Independent
Requires-Python: >=3.6
Requires-Dist: flask
